streambin
