Metadata-Version: 1.0
Name: streambin
Version: 0.2
Summary: Client for Streambin.net
Home-page: http://streambin.net/
Author: Soren Hansen
Author-email: soren@linux2go.dk
License: UNKNOWN
Platform: UNKNOWN
